Workbook

Sheet Overview
A1: Seeding QDArchive — Part 2 Classification Results
A2: Almas Ali Pinto (23123639) — Applied Software Engineering Project (10 ECTS)
A3: Generated 16 July 2026 from working.db
A5: Metric | B5: Value
A6: Total projects | B6: =COUNTA('Project Classifications'!$A$2:$A$100000) -> 230
A7: Projects classified (ISIC section assigned) | B7: =COUNTIFS('Project Classifications'!$F$2:$F$100000,"<>UNCLASSIFIED",'Project Classifications'!$F$2:$F$100000,"<>") -> 228
A8: Projects unclassified | B8: =COUNTIF('Project Classifications'!$F$2:$F$100000,"UNCLASSIFIED") -> 2
A9: Total files classified | B9: =COUNTA('File Classifications'!$A$2:$A$100000) -> 945
A10: Files classified from own content | B10: =COUNTIF('File Classifications'!$J$2:$J$100000,"RULE_BASED_KEYWORDS") -> 885
A11: Files inherited from parent project (no extractable text) | B11: =COUNTIF('File Classifications'!$J$2:$J$100000,"NO_TEXT_CONTENT") -> 60
A12: Distinct searchable tags | B12: =COUNTA(Tags!$A$2:$A$100000) -> 126
A13: ISIC sections represented | B13: =COUNTA('Section Distribution'!$A$2:$A$100000) -> 16
A14: ISIC divisions represented | B14: =COUNTA('Division Distribution'!$A$2:$A$100000) -> 20
A16: Methodology: rule-based keyword classifier scored against the complete official ISIC Rev. 5 taxonomy (22 sections, 87 divisions), using both project metadata and extracted file content. See classification/classifier.py and 23123639_SQ26_Part2_Report.pdf for full methodology and technical challenges.

Sheet Project Classifications
A1: project_id | B1: title | C1: repository | D1: download_method | E1: doi | F1: isic_section | G1: section_name | H1: isic_division | I1: division_name | J1: confidence | K1: method
A2: 1 | B2: Data for: Socializing Policy Feedback: The Persistent Effects of Adolescent Policy Program Use on Political Behaviors and Attitudes in Adulthood | C2: qdr | D2: API-CALL | E2: https://doi.org/10.5064/F6HYTYIJ | F2: P | G2: Public administration and defence; compulsory social security | H2: 84 | I2: Public administration and defence; compulsory social security | J2: 0.17647059 | K2: RULE_BASED_KEYWORDS
A3: 2 | B3: Interviews Regarding Data Curation for Qualitative Data Reuse and Big Social Research | C3: qdr | D3: API-CALL | E3: https://doi.org/10.5064/F6GWMU4O | F3: S | G3: Arts, sports and recreation | H3: 91 | I3: Library, archives, museum and other cultural activities | J3: 0.375 | K3: RULE_BASED_KEYWORDS
A4: 3 | B4: Data for: Exercise experiences in patients with metastatic lung cancer: A qualitative approach | C4: qdr | D4: API-CALL | E4: https://doi.org/10.5064/F6GEGCRX | F4: R | G4: Human health and social work activities | H4: 86 | I4: Human health activities | J4: 0.33333333 | K4: RULE_BASED_KEYWORDS
A5: 4 | B5: Data for: Teaching with Shared Data for Learning Qualitative Data Analysis: A Multi-Sited Case Study of Instructor and Student Experiences | C5: qdr | D5: API-CALL | E5: https://doi.org/10.5064/F6XZV8BZ | F5: Q | G5: Education | H5: 85 | I5: Education | J5: 0.625 | K5: RULE_BASED_KEYWORDS
A6: 5 | B6: Data for: Qualitative Data Sharing: Participant Understanding, Motivation, and Consent | C6: qdr | D6: API-CALL | E6: https://doi.org/10.5064/F6YYA3O3 | F6: K | G6: Telecommunications, computer programming, consultancy, computing infrastructure, and other information service activities | H6: 63 | I6: Computing infrastructure, data processing, hosting, and other information service activities | J6: 0.28571429 | K6: RULE_BASED_KEYWORDS
A7: 6 | B7: Data for: 'Perceptions on Ethical Considerations on the Conduct of Research During Disease Outbreaks in Nigeria by Policymakers and Ethicists' | C7: qdr | D7: API-CALL | E7: https://doi.org/10.5064/F6CMJ6F0 | F7: R | G7: Human health and social work activities | H7: 86 | I7: Human health activities | J7: 0.27777778 | K7: RULE_BASED_KEYWORDS
A8: 7 | B8: Recovery Experiences in Young Women with Acute Myocardial Infarction | C8: qdr | D8: API-CALL | E8: https://doi.org/10.5064/F66R7QMF | F8: R | G8: Human health and social work activities | H8: 86 | I8: Human health activities | J8: 0.33333333 | K8: RULE_BASED_KEYWORDS
A9: 8 | B9: Ethical Challenges When Engaging Patients and Families in End-of-Life and Palliative Care Research | C9: qdr | D9: API-CALL | E9: https://doi.org/10.5064/F6WKR6ED | F9: R | G9: Human health and social work activities | H9: 86 | I9: Human health activities | J9: 0.22222222 | K9: RULE_BASED_KEYWORDS
A10: 9 | B10: Data for: Assessing the Usability of a Novel Toolkit for Creating Visual Key Information Pages for Informed Consent for Research | C10: qdr | D10: API-CALL | E10: https://doi.org/10.5064/F6XJ82VS | F10: Q | G10: Education | H10: 85 | I10: Education | J10: 0.125 | K10: RULE_BASED_KEYWORDS
A11: 10 | B11: Optimizing Openness in Human Participants Research: Harmonizing Standards for Consent Agreements and Data Management Plans to Empower the Reuse of Sensitive Scientific Data | C11: qdr | D11: API-CALL | E11: https://doi.org/10.5064/F6RQA7AQ | F11: Q | G11: Education | H11: 85 | I11: Education | J11: 0.3125 | K11: RULE_BASED_KEYWORDS
A12: 11 | B12: Data for: Fostering Undergraduate Self-Confidence and Community in Solar/Astro-Physics: The Impact of Research Experiences and Public Outreach | C12: qdr | D12: API-CALL | E12: https://doi.org/10.5064/F6HH7SDG | F12: Q | G12: Education | H12: 85 | I12: Education | J12: 0.25 | K12: RULE_BASED_KEYWORDS
A13: 12 | B13: Marine Corps Organizational Culture Research (MCOCR) Project | C13: qdr | D13: API-CALL | E13: https://doi.org/10.5064/F6K4IVEP | F13: N | G13: Professional, scientific and technical activities | H13: 72 | I13: Scientific research and development | J13: 0.071428571 | K13: RULE_BASED_KEYWORDS
... A231: 230 | B231: Data for: “Pivotal deterrence and the chain gang: Sir Edward Grey’s ambiguous policy and the July Crisis,” in: Pivotal deterrence: Third-party statecraft and the pursuit of peace | C231: qdr | D231: API-CALL | E231: https://doi.org/10.5064/F6G44N6S | F231: K | G231: Telecommunications, computer programming, consultancy, computing infrastructure, and other information service activities | H231: 63 | I231: Computing infrastructure, data processing, hosting, and other information service activities | J231: 0.14285714 | K231: RULE_BASED_KEYWORDS

Sheet File Classifications
A1: file_id | B1: project_id | C1: project_title | D1: file_name | E1: file_type | F1: isic_section | G1: isic_division | H1: division_name | I1: confidence | J1: method
A2: 5 | B2: 1 | C2: =IFERROR(INDEX('Project Classifications'!$B$2:$B$231,MATCH(B2,'Project Classifications'!$A$2:$A$231,0)),"") -> Data for: Socializing Policy Feedback: The Persistent Effects of Adolescent Policy Program Use on Political Behaviors and Attitudes in Adulthood | D2: Micatka_AHPAS_SurveyInstrument.pdf | E2: pdf | F2: P | G2: 84 | H2: Public administration and defence; compulsory social security | I2: 0.23529412 | J2: RULE_BASED_KEYWORDS
A3: 7 | B3: 1 | C3: =IFERROR(INDEX('Project Classifications'!$B$2:$B$231,MATCH(B3,'Project Classifications'!$A$2:$A$231,0)),"") -> Data for: Socializing Policy Feedback: The Persistent Effects of Adolescent Policy Program Use on Political Behaviors and Attitudes in Adulthood | D3: Micatka_DataNarrative.pdf | E3: pdf | F3: P | G3: 84 | H3: Public administration and defence; compulsory social security | I3: 0.17647059 | J3: RULE_BASED_KEYWORDS
A4: 8 | B4: 1 | C4: =IFERROR(INDEX('Project Classifications'!$B$2:$B$231,MATCH(B4,'Project Classifications'!$A$2:$A$231,0)),"") -> Data for: Socializing Policy Feedback: The Persistent Effects of Adolescent Policy Program Use on Political Behaviors and Attitudes in Adulthood | D4: Micatka_InformationSheet_FocusGroup.pdf | E4: pdf | F4: P | G4: 84 | H4: Public administration and defence; compulsory social security | I4: 0.11764706 | J4: RULE_BASED_KEYWORDS
A5: 9 | B5: 1 | C5: =IFERROR(INDEX('Project Classifications'!$B$2:$B$231,MATCH(B5,'Project Classifications'!$A$2:$A$231,0)),"") -> Data for: Socializing Policy Feedback: The Persistent Effects of Adolescent Policy Program Use on Political Behaviors and Attitudes in Adulthood | D5: Micatka_InformationSheet_Interviews.pdf | E5: pdf | F5: P | G5: 84 | H5: Public administration and defence; compulsory social security | I5: 0.11764706 | J5: RULE_BASED_KEYWORDS
A6: 10 | B6: 1 | C6: =IFERROR(INDEX('Project Classifications'!$B$2:$B$231,MATCH(B6,'Project Classifications'!$A$2:$A$231,0)),"") -> Data for: Socializing Policy Feedback: The Persistent Effects of Adolescent Policy Program Use on Political Behaviors and Attitudes in Adulthood | D6: Micatka_InformationSheet_Questionnaire.pdf | E6: pdf | F6: P | G6: 84 | H6: Public administration and defence; compulsory social security | I6: 0.11764706 | J6: RULE_BASED_KEYWORDS
A7: 11 | B7: 1 | C7: =IFERROR(INDEX('Project Classifications'!$B$2:$B$231,MATCH(B7,'Project Classifications'!$A$2:$A$231,0)),"") -> Data for: Socializing Policy Feedback: The Persistent Effects of Adolescent Policy Program Use on Political Behaviors and Attitudes in Adulthood | D7: Micatka_InterviewInstrument_Poverty_Round3.pdf | E7: pdf | F7: P | G7: 84 | H7: Public administration and defence; compulsory social security | I7: 0.058823529 | J7: RULE_BASED_KEYWORDS
A8: 12 | B8: 1 | C8: =IFERROR(INDEX('Project Classifications'!$B$2:$B$231,MATCH(B8,'Project Classifications'!$A$2:$A$231,0)),"") -> Data for: Socializing Policy Feedback: The Persistent Effects of Adolescent Policy Program Use on Political Behaviors and Attitudes in Adulthood | D8: Micatka_InterviewInstrument_Round1_Round2.pdf | E8: pdf | F8: P | G8: 84 | H8: Public administration and defence; compulsory social security | I8: 0.11764706 | J8: RULE_BASED_KEYWORDS
A9: 13 | B9: 1 | C9: =IFERROR(INDEX('Project Classifications'!$B$2:$B$231,MATCH(B9,'Project Classifications'!$A$2:$A$231,0)),"") -> Data for: Socializing Policy Feedback: The Persistent Effects of Adolescent Policy Program Use on Political Behaviors and Attitudes in Adulthood | D9: Micatka_InterviewInstrument_Welfare_Round3.pdf | E9: pdf | F9: P | G9: 84 | H9: Public administration and defence; compulsory social security | I9: 0.11764706 | J9: RULE_BASED_KEYWORDS
A10: 14 | B10: 1 | C10: =IFERROR(INDEX('Project Classifications'!$B$2:$B$231,MATCH(B10,'Project Classifications'!$A$2:$A$231,0)),"") -> Data for: Socializing Policy Feedback: The Persistent Effects of Adolescent Policy Program Use on Political Behaviors and Attitudes in Adulthood | D10: Micatka_InterviewQuestionnaire_Round1.pdf | E10: pdf | F10: L | G10: 65 | H10: Insurance, reinsurance and pension funding, except compulsory social security | I10: 0.5 | J10: RULE_BASED_KEYWORDS
A11: 15 | B11: 1 | C11: =IFERROR(INDEX('Project Classifications'!$B$2:$B$231,MATCH(B11,'Project Classifications'!$A$2:$A$231,0)),"") -> Data for: Socializing Policy Feedback: The Persistent Effects of Adolescent Policy Program Use on Political Behaviors and Attitudes in Adulthood | D11: Micatka_InterviewQuestionnaire_Round2.pdf | E11: pdf | F11: L | G11: 65 | H11: Insurance, reinsurance and pension funding, except compulsory social security | I11: 0.5 | J11: RULE_BASED_KEYWORDS
A12: 16 | B12: 1 | C12: =IFERROR(INDEX('Project Classifications'!$B$2:$B$231,MATCH(B12,'Project Classifications'!$A$2:$A$231,0)),"") -> Data for: Socializing Policy Feedback: The Persistent Effects of Adolescent Policy Program Use on Political Behaviors and Attitudes in Adulthood | D12: Micatka_QualitativeProcedure_Details.pdf | E12: pdf | F12: P | G12: 84 | H12: Public administration and defence; compulsory social security | I12: 0.11764706 | J12: RULE_BASED_KEYWORDS
A13: 49 | B13: 1 | C13: =IFERROR(INDEX('Project Classifications'!$B$2:$B$231,MATCH(B13,'Project Classifications'!$A$2:$A$231,0)),"") -> Data for: Socializing Policy Feedback: The Persistent Effects of Adolescent Policy Program Use on Political Behaviors and Attitudes in Adulthood | D13: README_Micatka.txt | E13: txt | F13: P | G13: 84 | H13: Public administration and defence; compulsory social security | I13: 0.17647059 | J13: RULE_BASED_KEYWORDS
... A946: 20322 | B946: 230 | C946: =IFERROR(INDEX('Project Classifications'!$B$2:$B$231,MATCH(B946,'Project Classifications'!$A$2:$A$231,0)),"") -> Data for: “Pivotal deterrence and the chain gang: Sir Edward Grey’s ambiguous policy and the July Crisis,” in: Pivotal deterrence: Third-party statecraft and the pursuit of peace | D946: README_Crawford.txt | E946: txt | F946: K | G946: 63 | H946: Computing infrastructure, data processing, hosting, and other information service activities | I946: 0.28571429 | J946: RULE_BASED_KEYWORDS

Sheet Project-Tags
A1: project_id | B1: tag
A2: 34 | B2: academic research
A3: 38 | B3: academic research
A4: 68 | B4: academic research
A5: 80 | B5: accounting
A6: 149 | B6: advertising
A7: 199 | B7: advertising
A8: 40 | B8: agriculture
A9: 59 | B9: agriculture
A10: 73 | B10: agriculture
A11: 80 | B11: agriculture
A12: 200 | B12: animal health
A13: 188 | B13: architecture
... A1501: 53 | B1501: workforce

Sheet Tags
A1: tag | B1: project_count
A2: academic research | B2: =COUNTIF('Project-Tags'!$B$2:$B$100000,A2) -> 3
A3: accounting | B3: =COUNTIF('Project-Tags'!$B$2:$B$100000,A3) -> 1
A4: advertising | B4: =COUNTIF('Project-Tags'!$B$2:$B$100000,A4) -> 2
A5: agriculture | B5: =COUNTIF('Project-Tags'!$B$2:$B$100000,A5) -> 4
A6: animal health | B6: =COUNTIF('Project-Tags'!$B$2:$B$100000,A6) -> 1
A7: architecture | B7: =COUNTIF('Project-Tags'!$B$2:$B$100000,A7) -> 1
A8: archives | B8: =COUNTIF('Project-Tags'!$B$2:$B$100000,A8) -> 27
A9: arts | B9: =COUNTIF('Project-Tags'!$B$2:$B$100000,A9) -> 36
A10: asylum seekers | B10: =COUNTIF('Project-Tags'!$B$2:$B$100000,A10) -> 1
A11: cancer | B11: =COUNTIF('Project-Tags'!$B$2:$B$100000,A11) -> 8
A12: career transitions | B12: =COUNTIF('Project-Tags'!$B$2:$B$100000,A12) -> 1
A13: chronic illness | B13: =COUNTIF('Project-Tags'!$B$2:$B$100000,A13) -> 3
... A127: workforce | B127: =COUNTIF('Project-Tags'!$B$2:$B$100000,A127) -> 1

Sheet Section Distribution
A1: isic_section | B1: section_name | C1: project_count | D1: file_count
A2: R | B2: Human health and social work activities | C2: =COUNTIF('Project Classifications'!$F$2:$F$100000,A2) -> 73 | D2: =COUNTIF('File Classifications'!$F$2:$F$100000,A2) -> 226
A3: Q | B3: Education | C3: =COUNTIF('Project Classifications'!$F$2:$F$100000,A3) -> 65 | D3: =COUNTIF('File Classifications'!$F$2:$F$100000,A3) -> 250
A4: K | B4: Telecommunications, computer programming, consultancy, computing infrastructure, and other information service activities | C4: =COUNTIF('Project Classifications'!$F$2:$F$100000,A4) -> 48 | D4: =COUNTIF('File Classifications'!$F$2:$F$100000,A4) -> 179
A5: N | B5: Professional, scientific and technical activities | C5: =COUNTIF('Project Classifications'!$F$2:$F$100000,A5) -> 13 | D5: =COUNTIF('File Classifications'!$F$2:$F$100000,A5) -> 49
A6: P | B6: Public administration and defence; compulsory social security | C6: =COUNTIF('Project Classifications'!$F$2:$F$100000,A6) -> 7 | D6: =COUNTIF('File Classifications'!$F$2:$F$100000,A6) -> 30
A7: S | B7: Arts, sports and recreation | C7: =COUNTIF('Project Classifications'!$F$2:$F$100000,A7) -> 7 | D7: =COUNTIF('File Classifications'!$F$2:$F$100000,A7) -> 25
A8: A | B8: Agriculture, forestry and fishing | C8: =COUNTIF('Project Classifications'!$F$2:$F$100000,A8) -> 3 | D8: =COUNTIF('File Classifications'!$F$2:$F$100000,A8) -> 44
A9: F | B9: Construction | C9: =COUNTIF('Project Classifications'!$F$2:$F$100000,A9) -> 3 | D9: =COUNTIF('File Classifications'!$F$2:$F$100000,A9) -> 4
A10: O | B10: Administrative and support service activities | C10: =COUNTIF('Project Classifications'!$F$2:$F$100000,A10) -> 3 | D10: =COUNTIF('File Classifications'!$F$2:$F$100000,A10) -> 10
A11: UNCLASSIFIED | B11: Unclassified | C11: =COUNTIF('Project Classifications'!$F$2:$F$100000,A11) -> 2 | D11: =COUNTIF('File Classifications'!$F$2:$F$100000,A11) -> 101
A12: E | B12: Water supply; sewerage, waste management and remediation activities | C12: =COUNTIF('Project Classifications'!$F$2:$F$100000,A12) -> 1 | D12: =COUNTIF('File Classifications'!$F$2:$F$100000,A12) -> 1
A13: H | B13: Transportation and storage | C13: =COUNTIF('Project Classifications'!$F$2:$F$100000,A13) -> 1 | D13: =COUNTIF('File Classifications'!$F$2:$F$100000,A13) -> 9
... A17: V | B17: Activities of extraterritorial organizations and bodies | C17: =COUNTIF('Project Classifications'!$F$2:$F$100000,A17) -> 1 | D17: =COUNTIF('File Classifications'!$F$2:$F$100000,A17) -> 2

Sheet Division Distribution
A1: isic_section | B1: isic_division | C1: division_name | D1: project_count | E1: file_count | F1: avg_confidence
A2: R | B2: 86 | C2: Human health activities | D2: =COUNTIFS('Project Classifications'!$F$2:$F$100000,A2,'Project Classifications'!$H$2:$H$100000,B2) -> 73 | E2: =COUNTIFS('File Classifications'!$F$2:$F$100000,A2,'File Classifications'!$G$2:$G$100000,B2) -> 226 | F2: =IFERROR(AVERAGEIFS('Project Classifications'!$J$2:$J$100000,'Project Classifications'!$F$2:$F$100000,A2,'Project Classifications'!$H$2:$H$100000,B2),0) -> 0.28843227
A3: Q | B3: 85 | C3: Education | D3: =COUNTIFS('Project Classifications'!$F$2:$F$100000,A3,'Project Classifications'!$H$2:$H$100000,B3) -> 65 | E3: =COUNTIFS('File Classifications'!$F$2:$F$100000,A3,'File Classifications'!$G$2:$G$100000,B3) -> 250 | F3: =IFERROR(AVERAGEIFS('Project Classifications'!$J$2:$J$100000,'Project Classifications'!$F$2:$F$100000,A3,'Project Classifications'!$H$2:$H$100000,B3),0) -> 0.22980769
A4: K | B4: 63 | C4: Computing infrastructure, data processing, hosting, and other information service activities | D4: =COUNTIFS('Project Classifications'!$F$2:$F$100000,A4,'Project Classifications'!$H$2:$H$100000,B4) -> 48 | E4: =COUNTIFS('File Classifications'!$F$2:$F$100000,A4,'File Classifications'!$G$2:$G$100000,B4) -> 175 | F4: =IFERROR(AVERAGEIFS('Project Classifications'!$J$2:$J$100000,'Project Classifications'!$F$2:$F$100000,A4,'Project Classifications'!$H$2:$H$100000,B4),0) -> 0.22321429
A5: N | B5: 72 | C5: Scientific research and development | D5: =COUNTIFS('Project Classifications'!$F$2:$F$100000,A5,'Project Classifications'!$H$2:$H$100000,B5) -> 7 | E5: =COUNTIFS('File Classifications'!$F$2:$F$100000,A5,'File Classifications'!$G$2:$G$100000,B5) -> 17 | F5: =IFERROR(AVERAGEIFS('Project Classifications'!$J$2:$J$100000,'Project Classifications'!$F$2:$F$100000,A5,'Project Classifications'!$H$2:$H$100000,B5),0) -> 0.091836735
A6: P | B6: 84 | C6: Public administration and defence; compulsory social security | D6: =COUNTIFS('Project Classifications'!$F$2:$F$100000,A6,'Project Classifications'!$H$2:$H$100000,B6) -> 7 | E6: =COUNTIFS('File Classifications'!$F$2:$F$100000,A6,'File Classifications'!$G$2:$G$100000,B6) -> 30 | F6: =IFERROR(AVERAGEIFS('Project Classifications'!$J$2:$J$100000,'Project Classifications'!$F$2:$F$100000,A6,'Project Classifications'!$H$2:$H$100000,B6),0) -> 0.12605042
A7: S | B7: 91 | C7: Library, archives, museum and other cultural activities | D7: =COUNTIFS('Project Classifications'!$F$2:$F$100000,A7,'Project Classifications'!$H$2:$H$100000,B7) -> 6 | E7: =COUNTIFS('File Classifications'!$F$2:$F$100000,A7,'File Classifications'!$G$2:$G$100000,B7) -> 15 | F7: =IFERROR(AVERAGEIFS('Project Classifications'!$J$2:$J$100000,'Project Classifications'!$F$2:$F$100000,A7,'Project Classifications'!$H$2:$H$100000,B7),0) -> 0.3125
A8: N | B8: 74 | C8: Other professional, scientific and technical activities | D8: =COUNTIFS('Project Classifications'!$F$2:$F$100000,A8,'Project Classifications'!$H$2:$H$100000,B8) -> 5 | E8: =COUNTIFS('File Classifications'!$F$2:$F$100000,A8,'File Classifications'!$G$2:$G$100000,B8) -> 27 | F8: =IFERROR(AVERAGEIFS('Project Classifications'!$J$2:$J$100000,'Project Classifications'!$F$2:$F$100000,A8,'Project Classifications'!$H$2:$H$100000,B8),0) -> 0.3
A9: F | B9: 41 | C9: Construction of residential and non-residential buildings | D9: =COUNTIFS('Project Classifications'!$F$2:$F$100000,A9,'Project Classifications'!$H$2:$H$100000,B9) -> 3 | E9: =COUNTIFS('File Classifications'!$F$2:$F$100000,A9,'File Classifications'!$G$2:$G$100000,B9) -> 4 | F9: =IFERROR(AVERAGEIFS('Project Classifications'!$J$2:$J$100000,'Project Classifications'!$F$2:$F$100000,A9,'Project Classifications'!$H$2:$H$100000,B9),0) -> 0.5
A10: O | B10: 78 | C10: Employment activities | D10: =COUNTIFS('Project Classifications'!$F$2:$F$100000,A10,'Project Classifications'!$H$2:$H$100000,B10) -> 3 | E10: =COUNTIFS('File Classifications'!$F$2:$F$100000,A10,'File Classifications'!$G$2:$G$100000,B10) -> 8 | F10: =IFERROR(AVERAGEIFS('Project Classifications'!$J$2:$J$100000,'Project Classifications'!$F$2:$F$100000,A10,'Project Classifications'!$H$2:$H$100000,B10),0) -> 0.14285714
A11: A | B11: 01 | C11: Crop and animal production, hunting and related service activities | D11: =COUNTIFS('Project Classifications'!$F$2:$F$100000,A11,'Project Classifications'!$H$2:$H$100000,B11) -> 2 | E11: =COUNTIFS('File Classifications'!$F$2:$F$100000,A11,'File Classifications'!$G$2:$G$100000,B11) -> 39 | F11: =IFERROR(AVERAGEIFS('Project Classifications'!$J$2:$J$100000,'Project Classifications'!$F$2:$F$100000,A11,'Project Classifications'!$H$2:$H$100000,B11),0) -> 0.33333333
A12: UNCLASSIFIED | B12: 00 | C12: Unclassified | D12: =COUNTIFS('Project Classifications'!$F$2:$F$100000,A12,'Project Classifications'!$H$2:$H$100000,B12) -> 2 | E12: =COUNTIFS('File Classifications'!$F$2:$F$100000,A12,'File Classifications'!$G$2:$G$100000,B12) -> 101 | F12: =IFERROR(AVERAGEIFS('Project Classifications'!$J$2:$J$100000,'Project Classifications'!$F$2:$F$100000,A12,'Project Classifications'!$H$2:$H$100000,B12),0) -> 0
A13: A | B13: 02 | C13: Forestry and logging | D13: =COUNTIFS('Project Classifications'!$F$2:$F$100000,A13,'Project Classifications'!$H$2:$H$100000,B13) -> 1 | E13: =COUNTIFS('File Classifications'!$F$2:$F$100000,A13,'File Classifications'!$G$2:$G$100000,B13) -> 3 | F13: =IFERROR(AVERAGEIFS('Project Classifications'!$J$2:$J$100000,'Project Classifications'!$F$2:$F$100000,A13,'Project Classifications'!$H$2:$H$100000,B13),0) -> 0.5
... A21: V | B21: 99 | C21: Activities of extraterritorial organizations and bodies | D21: =COUNTIFS('Project Classifications'!$F$2:$F$100000,A21,'Project Classifications'!$H$2:$H$100000,B21) -> 1 | E21: =COUNTIFS('File Classifications'!$F$2:$F$100000,A21,'File Classifications'!$G$2:$G$100000,B21) -> 2 | F21: =IFERROR(AVERAGEIFS('Project Classifications'!$J$2:$J$100000,'Project Classifications'!$F$2:$F$100000,A21,'Project Classifications'!$H$2:$H$100000,B21),0) -> 0.66666667
